{
  "DHome": {
    "description": "Auto imported from components/d_home.vue"
  },
  "Landing": {
    "description": "Auto imported from components/landing.vue"
  },
  "Logo": {
    "description": "Auto imported from components/logo.vue"
  },
  "MHome": {
    "description": "Auto imported from components/m_home.vue"
  },
  "DesktopHeroSection": {
    "description": "Auto imported from components/desktop/heroSection.vue"
  },
  "DesktopNavbar": {
    "description": "Auto imported from components/desktop/Navbar.vue"
  },
  "DesktopSidebar": {
    "description": "Auto imported from components/desktop/sidebar.vue"
  },
  "MobileLandingActionsheet": {
    "description": "Auto imported from components/mobile/landing_actionsheet.vue"
  },
  "MobileNavbar": {
    "description": "Auto imported from components/mobile/Navbar.vue"
  },
  "MobilePlaylistcard": {
    "description": "Auto imported from components/mobile/playlistcard.vue"
  },
  "MobilePlaylistcardcol": {
    "description": "Auto imported from components/mobile/playlistcardcol.vue"
  },
  "UtilsBackbutton": {
    "description": "Auto imported from components/utils/backbutton.vue"
  },
  "UtilsCategorycard": {
    "description": "Auto imported from components/utils/categorycard.vue"
  },
  "UtilsCategorycardcol": {
    "description": "Auto imported from components/utils/categorycardcol.vue"
  },
  "UtilsNavbar": {
    "description": "Auto imported from components/utils/Navbar.vue"
  },
  "UtilsSearchbar": {
    "description": "Auto imported from components/utils/searchbar.vue"
  },
  "UtilsSubscribemodal": {
    "description": "Auto imported from components/utils/subscribemodal.vue"
  }
}
